pyMine/__init__.py
pyMine/engine.py
pyMine/test.py
pymine-1.0.6.dist-info/LICENSE
pymine-1.0.6.dist-info/METADATA
pymine-1.0.6.dist-info/WHEEL
pymine-1.0.6.dist-info/top_level.txt
pymine-1.0.6.dist-info/RECORD
