Metadata-Version: 2.1
Name: pymine
Version: 1.0.6
Summary: pyMine is open-source module for Python, helps you to create or play old classic Windows Mine game in Python Terminal enviorment.
Home-page: https://github.com/soroushmpour/pyMine
Author: Soroush M Pour
Author-email: soroushmpour@gmail.com
License: UNKNOWN
Platform: UNKNOWN
Classifier: Programming Language :: Python :: 3
Classifier: License :: OSI Approved :: GNU General Public License (GPL)
Classifier: Operating System :: OS Independent
